{
    "Andhra Pradesh": {
        "Visakhapatnam": [
            "530001",
            "530003",
            "530017",
            "530026",
            "530045"
        ],
        "Vijayawada": [
            "520001",
            "520002",
            "520010",
            "520012"
        ],
        "Guntur": [
            "522001",
            "522002",
            "522004",
            "522007"
        ],
        "Nellore": [
            "524001",
            "524002",
            "524003",
            "524004"
        ],
        "Kurnool": [
            "518001",
            "518002",
            "518003",
            "518004"
        ],
        "Rajahmundry": [
            "533101",
            "533102",
            "533103",
            "533105"
        ],
        "Tirupati": [
            "517501",
            "517502",
            "517507"
        ],
        "Kakinada": [
            "533001",
            "533003",
            "533004",
            "533005"
        ],
        "Kadapa": [
            "516001",
            "516002",
            "516003",
            "516004"
        ],
        "Anantapur": [
            "515001",
            "515002",
            "515004"
        ],
        "Vizianagaram": [
            "535001",
            "535002",
            "535003"
        ],
        "Eluru": [
            "534001",
            "534002",
            "534005"
        ],
        "Ongole": [
            "523001",
            "523002"
        ],
        "Nandyal": [
            "518501",
            "518502"
        ],
        "Chittoor": [
            "517001",
            "517002"
        ],
        "Machilipatnam": [
            "521001",
            "521002"
        ],
        "Adoni": [
            "518301",
            "518302"
        ],
        "Tenali": [
            "522201",
            "522202"
        ],
        "Proddatur": [
            "516360",
            "516361"
        ],
        "Hindupur": [
            "515201"
        ],
        "Bhimavaram": [
            "534201",
            "534202"
        ],
        "Madanapalle": [
            "517325",
            "517326"
        ],
        "Srikakulam": [
            "532001",
            "532005"
        ],
        "Narasaraopet": [
            "522601"
        ],
        "Tadipatri": [
            "515411"
        ],
        "Guntakal": [
            "515801"
        ]
    },
    "Telangana": {
        "Hyderabad": [
            "500001",
            "500002",
            "500003",
            "500004",
            "500005",
            "500018",
            "500032",
            "500033",
            "500034",
            "500081",
            "500082"
        ],
        "Warangal": [
            "506001",
            "506002",
            "506007",
            "506009"
        ],
        "Nizamabad": [
            "503001",
            "503002",
            "503003"
        ],
        "Khammam": [
            "507001",
            "507002",
            "507003"
        ],
        "Karimnagar": [
            "505001",
            "505002"
        ],
        "Ramagundam": [
            "505208",
            "505209",
            "505210"
        ],
        "Mahbubnagar": [
            "509001",
            "509002"
        ],
        "Nalgonda": [
            "508001",
            "508002"
        ],
        "Adilabad": [
            "504001",
            "504002"
        ],
        "Suryapet": [
            "508213"
        ],
        "Miryalaguda": [
            "508207"
        ],
        "Siddipet": [
            "502103"
        ],
        "Jagtial": [
            "505327"
        ],
        "Mancherial": [
            "504208"
        ],
        "Kothagudem": [
            "507101"
        ],
        "Nirmal": [
            "504106"
        ],
        "Kamareddy": [
            "503111"
        ],
        "Bodhan": [
            "503185"
        ],
        "Palwancha": [
            "507115"
        ],
        "Siricilla": [
            "505301"
        ],
        "Kagaznagar": [
            "504296"
        ],
        "Gadwal": [
            "509125"
        ],
        "Wanaparthy": [
            "509103"
        ],
        "Vikarabad": [
            "501101"
        ],
        "Jangaon": [
            "506167"
        ]
    }
}